simpledms/__init__.py
simpledms/__main__.py
simpledms/main.py
simpledms/pdfhandler.py
simpledms/rules.py
simpledms/ui/__init__.py
simpledms/ui/about.py
simpledms/ui/about.ui
simpledms/ui/editrules.py
simpledms/ui/editrules.ui
simpledms/ui/icons/outline_add_circle_outline_white_18dp.png
simpledms/ui/icons/outline_archive_white_18dp.png
simpledms/ui/icons/outline_build_white_18dp.png
simpledms/ui/icons/outline_calendar_today_white_18dp.png
simpledms/ui/icons/outline_cancel_white_18dp.png
simpledms/ui/icons/outline_check_white_18dp.png
simpledms/ui/icons/outline_clear_white_18dp.png
simpledms/ui/icons/outline_description_white_18dp.png
simpledms/ui/icons/outline_exit_to_app_white_18dp.png
simpledms/ui/icons/outline_get_app_white_18dp.png
simpledms/ui/icons/outline_info_white_18dp.png
simpledms/ui/icons/outline_remove_circle_outline_white_18dp.png
simpledms/ui/icons/outline_scanner_white_18dp.png
simpledms/ui/icons/outline_search_white_18dp.png
simpledms/ui/icons/outline_search_white_18dp1.png
simpledms/ui/icons/outline_settings_white_18dp.png
simpledms/ui/main_simpledms.py
simpledms/ui/main_simpledms.qrc
simpledms/ui/main_simpledms.ui
simpledms/ui/main_simpledms_rc.py
simpledms/ui/resources.py
simpledms/utils.py
simpledms-0.1.4.dist-info/LICENSE
simpledms-0.1.4.dist-info/WHEEL
simpledms-0.1.4.dist-info/METADATA
simpledms-0.1.4.dist-info/RECORD
